pyogpclient/OGPClient.py
pyogpclient/__init__.py
pyogpclient-0.0.1.dist-info/LICENSE
pyogpclient-0.0.1.dist-info/METADATA
pyogpclient-0.0.1.dist-info/WHEEL
pyogpclient-0.0.1.dist-info/top_level.txt
pyogpclient-0.0.1.dist-info/RECORD
