Metadata-Version: 2.1
Name: pyogpclient
Version: 0.0.1
Summary: Open Game Protocol Client for Python 3
Home-page: https://github.com/JanHolger/pyogpclient
Author: Jan Bebendorf
Author-email: jan@bebendorf.eu
License: UNKNOWN
Platform: UNKNOWN
Classifier: Programming Language :: Python :: 3
Classifier: License :: OSI Approved :: Apache Software License
Classifier: Operating System :: OS Independent
Requires-Python: >=3.6
